credo_pay/__init__.py
credo_pay/admin.py
credo_pay/apps.py
credo_pay/client.py
credo_pay/config.py
credo_pay/exceptions.py
credo_pay/mixins.py
credo_pay/models.py
credo_pay/serializers.py
credo_pay/urls.py
credo_pay/views.py
credo_pay/migrations/__init__.py
credo_pay/services/__init__.py
credo_pay/services/payment.py
credo_pay/services/webhook.py
credo_pay/templates/credo_pay/debug.html
credo_pay/templates/credo_pay/partials/config_check.html
credo_pay/templates/credo_pay/partials/payment_result.html
credo_pay/templates/credo_pay/partials/verify_result.html
credo_pay/templates/credo_pay/partials/webhook_payload.html
credo_pay/utils/__init__.py
credo_pay/utils/callback.py
credo_pay/utils/signature.py
credo_pay/utils/validators.py
django_credo_sdk-0.1.1.dist-info/licenses/LICENSE
django_credo_sdk-0.1.1.dist-info/METADATA
django_credo_sdk-0.1.1.dist-info/WHEEL
django_credo_sdk-0.1.1.dist-info/top_level.txt
django_credo_sdk-0.1.1.dist-info/RECORD
