Metadata-Version: 2.4
Name: django-credo-sdk
Version: 0.1.1
Summary: Unofficial Django SDK for Credo payment integration
Author-email: Samox <emyjunio925@gmail.com>
License: MIT License
Project-URL: Homepage, https://github.com/onuigb0/django-credo-sdk
Project-URL: Bug Tracker, https://github.com/onuigb0/django-credo-sdk/issues
Project-URL: Documentation, https://github.com/onuigb0/django-credo-sdk#readme
Project-URL: Source Code, https://github.com/onuigb0/django-credo-sdk
Keywords: django,credo,payments,sdk,payment-gateway,nigeria,fintech
Classifier: Development Status :: 4 - Beta
Classifier: Intended Audience :: Developers
Classifier: License :: OSI Approved :: MIT License
Classifier: Programming Language :: Python :: 3
Classifier: Programming Language :: Python :: 3.8
Classifier: Programming Language :: Python :: 3.9
Classifier: Programming Language :: Python :: 3.10
Classifier: Programming Language :: Python :: 3.11
Classifier: Programming Language :: Python :: 3.12
Classifier: Framework :: Django
Classifier: Framework :: Django :: 4.0
Classifier: Framework :: Django :: 4.1
Classifier: Framework :: Django :: 4.2
Classifier: Framework :: Django :: 5.0
Classifier: Framework :: Django :: 6.0
Classifier: Topic :: Software Development :: Libraries :: Python Modules
Classifier: Topic :: Office/Business :: Financial
Requires-Python: >=3.8
License-File: LICENSE
Requires-Dist: django>=4.0
Requires-Dist: djangorestframework>=3.14.0
Requires-Dist: requests>=2.0
Dynamic: license-file
